PythonQianghuaXuexiShiyongZhinanChuyiFix1/README.md
PythonQianghuaXuexiShiyongZhinanChuyiFix1/__init__.py
PythonQianghuaXuexiShiyongZhinanChuyiFix1/__main__.py
PythonQianghuaXuexiShiyongZhinanChuyiFix1/file.epub
PythonQianghuaXuexiShiyongZhinanChuyiFix1/index.html
PythonQianghuaXuexiShiyongZhinanChuyiFix1/css/__init__.py
PythonQianghuaXuexiShiyongZhinanChuyiFix1/css/annotations.css
PythonQianghuaXuexiShiyongZhinanChuyiFix1/css/main.css
PythonQianghuaXuexiShiyongZhinanChuyiFix1/css/normalize.css
PythonQianghuaXuexiShiyongZhinanChuyiFix1/css/popup.css
PythonQianghuaXuexiShiyongZhinanChuyiFix1/font/__init__.py
PythonQianghuaXuexiShiyongZhinanChuyiFix1/font/fontello.eot
PythonQianghuaXuexiShiyongZhinanChuyiFix1/font/fontello.svg
PythonQianghuaXuexiShiyongZhinanChuyiFix1/font/fontello.ttf
PythonQianghuaXuexiShiyongZhinanChuyiFix1/font/fontello.woff
PythonQianghuaXuexiShiyongZhinanChuyiFix1/img/__init__.py
PythonQianghuaXuexiShiyongZhinanChuyiFix1/img/annotator-glyph-sprite.png
PythonQianghuaXuexiShiyongZhinanChuyiFix1/img/annotator-icon-sprite.png
PythonQianghuaXuexiShiyongZhinanChuyiFix1/img/apple-touch-icon.png
PythonQianghuaXuexiShiyongZhinanChuyiFix1/img/cancelfullscreen.png
PythonQianghuaXuexiShiyongZhinanChuyiFix1/img/close.png
PythonQianghuaXuexiShiyongZhinanChuyiFix1/img/fullscreen.png
PythonQianghuaXuexiShiyongZhinanChuyiFix1/img/loader.gif
PythonQianghuaXuexiShiyongZhinanChuyiFix1/img/menu-icon.png
PythonQianghuaXuexiShiyongZhinanChuyiFix1/img/save.png
PythonQianghuaXuexiShiyongZhinanChuyiFix1/img/saved.png
PythonQianghuaXuexiShiyongZhinanChuyiFix1/img/settings-s.png
PythonQianghuaXuexiShiyongZhinanChuyiFix1/img/settings.png
PythonQianghuaXuexiShiyongZhinanChuyiFix1/img/star.png
PythonQianghuaXuexiShiyongZhinanChuyiFix1/js/__init__.py
PythonQianghuaXuexiShiyongZhinanChuyiFix1/js/epub.js
PythonQianghuaXuexiShiyongZhinanChuyiFix1/js/epub.min.js
PythonQianghuaXuexiShiyongZhinanChuyiFix1/js/epub.min.map
PythonQianghuaXuexiShiyongZhinanChuyiFix1/js/hooks.min.js
python_qianghua_xuexi_shiyong_zhinan_chuyi_fix1-2025.3.25.1.dist-info/METADATA
python_qianghua_xuexi_shiyong_zhinan_chuyi_fix1-2025.3.25.1.dist-info/WHEEL
python_qianghua_xuexi_shiyong_zhinan_chuyi_fix1-2025.3.25.1.dist-info/entry_points.txt
python_qianghua_xuexi_shiyong_zhinan_chuyi_fix1-2025.3.25.1.dist-info/top_level.txt
python_qianghua_xuexi_shiyong_zhinan_chuyi_fix1-2025.3.25.1.dist-info/RECORD
